django_custom_structure/__init__.py
django_custom_structure/__main__.py
django_custom_structure/app_config.py
django_custom_structure/app_setup.py
django_custom_structure/base_data.py
django_custom_structure/docker_data.py
django_custom_structure/git_data.py
django_custom_structure/project_setup.py
django_custom_structure/setting_data.py
brickdjango-0.3.1.dist-info/METADATA
brickdjango-0.3.1.dist-info/WHEEL
brickdjango-0.3.1.dist-info/entry_points.txt
brickdjango-0.3.1.dist-info/top_level.txt
brickdjango-0.3.1.dist-info/RECORD
