Metadata-Version: 2.4
Name: brickdjango
Version: 0.3.1
Summary: A custom Django project structure optimized for scalability, modularity, and maintainability—ideal for both small and large-scale web applications.
Author: Amol Balpande
Author-email: Amol Balpande <amolbalpande2020@gmail.com>
Keywords: django,project-structure,starter,boilerplate,brick django
Requires-Python: >=3.8
Requires-Dist: Django>=4.0
Dynamic: author
Dynamic: requires-python
